zurch/__init__.py
zurch/__main__.py
zurch/cli.py
zurch/collections.py
zurch/config.py
zurch/config_models.py
zurch/config_pydantic.py
zurch/config_wizard.py
zurch/constants.py
zurch/database.py
zurch/display.py
zurch/duplicates.py
zurch/export.py
zurch/handlers.py
zurch/hierarchical_pagination.py
zurch/interactive.py
zurch/items.py
zurch/keyboard.py
zurch/metadata.py
zurch/models.py
zurch/notes.py
zurch/pagination.py
zurch/parser.py
zurch/pydantic_models.py
zurch/queries.py
zurch/search.py
zurch/spinner.py
zurch/stats.py
zurch/utils.py
zurch-0.7.9.dist-info/METADATA
zurch-0.7.9.dist-info/WHEEL
zurch-0.7.9.dist-info/entry_points.txt
zurch-0.7.9.dist-info/licenses/LICENSE
zurch-0.7.9.dist-info/RECORD
