Metadata-Version: 2.4
Name: zurch
Version: 0.7.9
Summary: Zurch - A CLI search tool for Zotero installations
Project-URL: Homepage, https://github.com/kmlawson/zurch
Project-URL: Repository, https://github.com/kmlawson/zurch.git
Project-URL: Issues, https://github.com/kmlawson/zurch/issues
Author-email: "Konrad M. Lawson" <kmlawson@gmail.com>
License: MIT
License-File: LICENSE
Keywords: bibliography,cli,research,search,zotero
Classifier: Development Status :: 4 - Beta
Classifier: Environment :: Console
Classifier: Intended Audience :: Science/Research
Classifier: License :: OSI Approved :: MIT License
Classifier: Operating System :: OS Independent
Classifier: Programming Language :: Python :: 3
Classifier: Programming Language :: Python :: 3.8
Classifier: Programming Language :: Python :: 3.9
Classifier: Programming Language :: Python :: 3.10
Classifier: Programming Language :: Python :: 3.11
Classifier: Programming Language :: Python :: 3.12
Classifier: Topic :: Scientific/Engineering
Classifier: Topic :: Utilities
Requires-Python: >=3.8
Requires-Dist: jsonschema>=4.0.0
Requires-Dist: pydantic>=2.0.0
